dScriptModule/__init__.py
dScriptModule/dScriptBoard.py
dScriptModule/dScriptEvent.py
dScriptModule/dScriptObject.py
dScriptModule/dScriptServer.py
dScriptModule/dScriptVirtualBoard.py
dScriptModule-3.4.5.dist-info/LICENSE
dScriptModule-3.4.5.dist-info/METADATA
dScriptModule-3.4.5.dist-info/WHEEL
dScriptModule-3.4.5.dist-info/top_level.txt
dScriptModule-3.4.5.dist-info/RECORD
