Metadata-Version: 2.1
Name: dScriptModule
Version: 3.4.5
Summary: Home Assistant ready python module for dScript boards (by Robot-Electronics / Devantech Ltd.) with CUSTOM app firmware
Home-page: https://github.com/mk-maddin/dScriptModule
Author: Martin Kraemer
Author-email: mk.maddin@gmail.com
License: UNKNOWN
Platform: UNKNOWN
Classifier: Programming Language :: Python :: 3
Classifier: License :: OSI Approved :: GNU General Public License v3 (GPLv3)
Classifier: Operating System :: OS Independent
Requires-Python: >=3.7
Requires-Dist: bitstring
Requires-Dist: pycryptodome
